[
  {
    "ContainingType": "product_pricing.Controllers.ProductsController",
    "Method": "GetAll",
    "RelativePath": "api/Products",
    "HttpMethod": "GET",
    "IsController": true,
    "Order": 0,
    "Parameters": [],
    "ReturnTypes": [
      {
        "Type": "System.Collections.Generic.List\u00601[[ProductPricing.Shared.Dtos.ProductListItemDto, ProductPricing.Shared, Version=1.0.0.0, Culture=neutral, PublicKeyToken=null]]",
        "MediaTypes": [
          "text/plain",
          "application/json",
          "text/json"
        ],
        "StatusCode": 200
      }
    ]
  },
  {
    "ContainingType": "product_pricing.Controllers.ProductsController",
    "Method": "GetHistory",
    "RelativePath": "api/Products/{id}",
    "HttpMethod": "GET",
    "IsController": true,
    "Order": 0,
    "Parameters": [
      {
        "Name": "id",
        "Type": "System.Int32",
        "IsRequired": true
      }
    ],
    "ReturnTypes": [
      {
        "Type": "ProductPricing.Shared.Dtos.ProductHistoryDto",
        "MediaTypes": [
          "text/plain",
          "application/json",
          "text/json"
        ],
        "StatusCode": 200
      }
    ]
  },
  {
    "ContainingType": "product_pricing.Controllers.ProductsController",
    "Method": "ApplyDiscount",
    "RelativePath": "api/Products/{id}/apply-discount",
    "HttpMethod": "POST",
    "IsController": true,
    "Order": 0,
    "Parameters": [
      {
        "Name": "id",
        "Type": "System.Int32",
        "IsRequired": true
      },
      {
        "Name": "request",
        "Type": "ProductPricing.Shared.Dtos.ApplyDiscountRequest",
        "IsRequired": true
      }
    ],
    "ReturnTypes": [
      {
        "Type": "ProductPricing.Shared.Dtos.ApplyDiscountDto",
        "MediaTypes": [
          "text/plain",
          "application/json",
          "text/json"
        ],
        "StatusCode": 200
      }
    ]
  },
  {
    "ContainingType": "product_pricing.Controllers.ProductsController",
    "Method": "UpdatePrice",
    "RelativePath": "api/Products/{id}/update-price",
    "HttpMethod": "PUT",
    "IsController": true,
    "Order": 0,
    "Parameters": [
      {
        "Name": "id",
        "Type": "System.Int32",
        "IsRequired": true
      },
      {
        "Name": "request",
        "Type": "ProductPricing.Shared.Dtos.UpdatePriceRequest",
        "IsRequired": true
      }
    ],
    "ReturnTypes": [
      {
        "Type": "ProductPricing.Shared.Dtos.UpdatePriceDto",
        "MediaTypes": [
          "text/plain",
          "application/json",
          "text/json"
        ],
        "StatusCode": 200
      }
    ]
  }
]